Practical-4/Practical-4/src/Parameter.v
// =========================================================================
// Practical 4: StarCore-1 — Single-Cycle Processor in Verilog
// =========================================================================
//
// GROUP NUMBER: 22
//
// MEMBERS:
//   - Member 1 Samson Okuthe, OKTSAM001
//   - Member 2 Nyakallo Peete, PTXNYA001

// File        : Parameter.v
// Description : Shared compile-time parameters used across all modules.
//               Include this file at the top of every .v file:
//                   `include "../src/Parameter.v"
// =============================================================================

`ifndef PARAMETER_H_
`define PARAMETER_H_

// ---------------------------------------------------------------------------
// Memory dimensions
// ---------------------------------------------------------------------------
`define COL     16          // Data/instruction word width (bits)
`define ROW_I   16          // Instruction memory depth (words, 16 x 16-bit)
`define ROW_D    8          // Data memory depth (words,  8 x 16-bit)

// ---------------------------------------------------------------------------
// Simulation control
// Increase SIM_TIME if your test program needs more clock cycles to complete.
// At 10 ns per clock (100 MHz) each #10 is one half-period; 320 ns = 16 cycles.
// ---------------------------------------------------------------------------
`define SIM_TIME  #640      // Total simulation time for integration testbench

// ---------------------------------------------------------------------------
// Output file for data-memory dump (used in DataMemory.v $fmonitor)
// ---------------------------------------------------------------------------
`define DMEM_LOG  "./waves/dmem_log.txt"

`endif  // PARAMETER_H_

Practical-4/src/DataMemory.v
// =========================================================================
// Practical 4: StarCore-1 — Single-Cycle Processor in Verilog
// =========================================================================
// File        : DataMemory.v
// Description : 8-word data RAM. Sync write, async read (gated by mem_read).
//               Address indexing: ram_addr = mem_access_addr[2:0]

`timescale 1ns / 1ps
`include "../src/Parameter.v"

module DataMemory (
    input        clk,
    input  [15:0] mem_access_addr,
    input  [15:0] mem_write_data,
    input        mem_write_en,
    input        mem_read,
    output [15:0] mem_read_data
);

    reg [`COL-1:0] memory [`ROW_D-1:0];

    // Word address: lower 3 bits of byte address
    wire [2:0] ram_addr = mem_access_addr[2:0];

    integer log_fd;
    initial begin
        $readmemb("./test.data", memory, 0, 7);
    end

    // Synchronous write
    always @(posedge clk) begin
        if (mem_write_en)
            memory[ram_addr] <= mem_write_data;
    end

    // Combinational gated read
    assign mem_read_data = mem_read ? memory[ram_addr] : 16'd0;

endmodule

Practical-4/tb/DataMemory_tb.v
// =============================================================================
// EEE4120F Practical 4 — StarCore-1 Processor
// File        : DataMemory_tb.v
// =============================================================================
`timescale 1ns / 1ps
`include "../src/Parameter.v"

module DataMemory_tb;

    reg        clk;
    reg  [15:0] mem_access_addr;
    reg  [15:0] mem_write_data;
    reg        mem_write_en;
    reg        mem_read;
    wire [15:0] mem_read_data;

    DataMemory uut (
        .clk             (clk),
        .mem_access_addr (mem_access_addr),
        .mem_write_data  (mem_write_data),
        .mem_write_en    (mem_write_en),
        .mem_read        (mem_read),
        .mem_read_data   (mem_read_data)
    );

    initial clk = 1'b0;
    always  #5 clk = ~clk;

    initial begin
        $dumpfile("../waves/dm_tb.vcd");
        $dumpvars(0, DataMemory_tb);
    end

    integer fail_count;
    integer test_id;
    initial begin
        fail_count = 0; test_id = 1;
        mem_write_en = 1'b0; mem_read = 1'b0;
        mem_access_addr = 16'd0; mem_write_data = 16'd0;
    end

    task check16;
        input [15:0] got;
        input [15:0] expected;
        input [63:0] id;
        begin
            if (got !== expected) begin
                $display("FAIL [T%0d]: got=0x%h, expected=0x%h", id, got, expected);
                fail_count = fail_count + 1;
            end else
                $display("PASS [T%0d]: value=0x%h", id, got);
        end
    endtask

    integer i;

    initial begin
        $display("=== DataMemory Testbench ===");
        @(posedge clk); #1; // let init settle

        // ── Group 1: Verify $readmemb initialisation ──────────────
        // test.data: [0]=1,[1]=2,[2]=3,[3]=4,[4]=5,[5]=6,[6]=7,[7]=8
        $display("--- Group 1: Verify $readmemb initialisation ---");
        for (i = 0; i < 8; i = i + 1) begin
            mem_access_addr = i[15:0];  // addr[2:0] = word index
            mem_read = 1'b1; #5;
            check16(mem_read_data, i[15:0] + 16'd1, test_id);
            test_id = test_id + 1;
        end
        mem_read = 1'b0;

        // ── Group 2: mem_read=0 gates output to 0 ────────────────
        $display("--- Group 2: Output is 0 when mem_read=0 ---");
        mem_access_addr = 16'd0; mem_read = 1'b0; #5;
        check16(mem_read_data, 16'd0, test_id); test_id = test_id + 1;

        // ── Group 3: Synchronous write then read back ─────────────
        $display("--- Group 3: Synchronous write then read back ---");
        mem_access_addr = 16'd2; mem_write_data = 16'hABCD;
        mem_write_en = 1'b1; mem_read = 1'b0;
        @(posedge clk); #1;
        mem_write_en = 1'b0; mem_read = 1'b1; #5;
        check16(mem_read_data, 16'hABCD, test_id); test_id = test_id + 1;

        // ── Group 4: Disabled write does not change memory ────────
        $display("--- Group 4: Disabled write leaves memory unchanged ---");
        mem_access_addr = 16'd4; mem_write_data = 16'hDEAD;
        mem_write_en = 1'b0;
        @(posedge clk); #1;
        mem_read = 1'b1; #5;
        check16(mem_read_data, 16'd5, test_id); test_id = test_id + 1; // original value
        mem_read = 1'b0;

        // ── Group 5: Write to max address (word[7]) ───────────────
        $display("--- Group 5: Write and read word[7] ---");
        mem_access_addr = 16'd7; mem_write_data = 16'h1234;
        mem_write_en = 1'b1;
        @(posedge clk); #1;
        mem_write_en = 1'b0; mem_read = 1'b1; #5;
        check16(mem_read_data, 16'h1234, test_id); test_id = test_id + 1;

        $display("");
        if (fail_count == 0)
            $display("=== ALL %0d TESTS PASSED ===", test_id - 1);
        else
            $display("=== %0d / %0d TESTS FAILED ===", fail_count, test_id - 1);
        $finish;
    end

endmodule

Practical-4/waves/dm_tb.vcd
$date
	Wed Apr 22 04:24:00 2026
$end
$version
	Icarus Verilog
$end
$timescale
	1ps
$end
$scope module DataMemory_tb $end
$var wire 16 ! mem_read_data [15:0] $end
$var reg 1 " clk $end
$var reg 16 # mem_access_addr [15:0] $end
$var reg 1 $ mem_read $end
$var reg 16 % mem_write_data [15:0] $end
$var reg 1 & mem_write_en $end
$var integer 32 ' fail_count [31:0] $end
$var integer 32 ( i [31:0] $end
$var integer 32 ) test_id [31:0] $end
$scope module uut $end
$var wire 1 " clk $end
$var wire 16 * mem_access_addr [15:0] $end
$var wire 1 $ mem_read $end
$var wire 16 + mem_write_data [15:0] $end
$var wire 1 & mem_write_en $end
$var wire 3 , ram_addr [2:0] $end
$var wire 16 - mem_read_data [15:0] $end
$upscope $end
$scope task check16 $end
$var reg 16 . expected [15:0] $end
$var reg 16 / got [15:0] $end
$var reg 64 0 id [63:0] $end
$upscope $end
$upscope $end
$enddefinitions $end
$comment Show the parameter values. $end
$dumpall
$end
#0
$dumpvars
bx 0
bx /
bx .
b0 -
b0 ,
b0 +
b0 *
b1 )
bx (
b0 '
0&
b0 %
0$
b0 #
0"
b0 !
$end
#5000
1"
#6000
b1 !
b1 -
1$
b0 (
#10000
0"
#11000
b10 !
b10 -
b1 ,
b1 #
b1 *
b1 (
b10 )
b1 0
b1 .
b1 /
#15000
1"
#16000
b11 !
b11 -
b10 ,
b10 #
b10 *
b10 (
b11 )
b10 0
b10 .
b10 /
#20000
0"
#21000
b100 !
b100 -
b11 ,
b11 #
b11 *
b11 (
b100 )
b11 0
b11 .
b11 /
#25000
1"
#26000
b101 !
b101 -
b100 ,
b100 #
b100 *
b100 (
b101 )
b100 0
b100 .
b100 /
#30000
0"
#31000
b110 !
b110 -
b101 ,
b101 #
b101 *
b101 (
b110 )
b101 0
b101 .
b101 /
#35000
1"
#36000
b111 !
b111 -
b110 ,
b110 #
b110 *
b110 (
b111 )
b110 0
b110 .
b110 /
#40000
0"
#41000
b1000 !
b1000 -
b111 ,
b111 #
b111 *
b111 (
b1000 )
b111 0
b111 .
b111 /
#45000
1"
#46000
b0 ,
b0 !
b0 -
b0 #
b0 *
0$
b1000 (
b1001 )
b1000 0
b1000 .
b1000 /
#50000
0"
#51000
b10 ,
1&
b1010101111001101 %
b1010101111001101 +
b10 #
b10 *
b1010 )
b1001 0
b0 .
b0 /
#55000
1"
#56000
b1010101111001101 !
b1010101111001101 -
1$
0&
#60000
0"
#61000
b101 !
b101 -
b100 ,
b1101111010101101 %
b1101111010101101 +
b100 #
b100 *
b1011 )
b1010 0
b1010101111001101 .
b1010101111001101 /
#65000
1"
#70000
0"
#71000
b111 ,
b0 !
b0 -
1&
b1001000110100 %
b1001000110100 +
b111 #
b111 *
0$
b1100 )
b1011 0
b101 .
b101 /
#75000
1"
#76000
b1001000110100 !
b1001000110100 -
1$
0&
#80000
0"
#81000
b1101 )
b1100 0
b1001000110100 .
b1001000110100 /
