Practical-4/Practical-4/src/Parameter.v
// =========================================================================
// Practical 4: StarCore-1 — Single-Cycle Processor in Verilog
// =========================================================================
//
// GROUP NUMBER: 22
//
// MEMBERS:
//   - Member 1 Samson Okuthe, OKTSAM001
//   - Member 2 Nyakallo Peete, PTXNYA001

// File        : Parameter.v
// Description : Shared compile-time parameters used across all modules.
//               Include this file at the top of every .v file:
//                   `include "../src/Parameter.v"
// =============================================================================

`ifndef PARAMETER_H_
`define PARAMETER_H_

// ---------------------------------------------------------------------------
// Memory dimensions
// ---------------------------------------------------------------------------
`define COL     16          // Data/instruction word width (bits)
`define ROW_I   16          // Instruction memory depth (words, 16 x 16-bit)
`define ROW_D    8          // Data memory depth (words,  8 x 16-bit)

// ---------------------------------------------------------------------------
// Simulation control
// Increase SIM_TIME if your test program needs more clock cycles to complete.
// At 10 ns per clock (100 MHz) each #10 is one half-period; 320 ns = 16 cycles.
// ---------------------------------------------------------------------------
`define SIM_TIME  #640      // Total simulation time for integration testbench

// ---------------------------------------------------------------------------
// Output file for data-memory dump (used in DataMemory.v $fmonitor)
// ---------------------------------------------------------------------------
`define DMEM_LOG  "./waves/dmem_log.txt"

`endif  // PARAMETER_H_

Practical-4/Practical-4/src/GPR.v
// =========================================================================
// Practical 4: StarCore-1 — Single-Cycle Processor in Verilog
// =========================================================================
//
// GROUP NUMBER: 22
//
// MEMBERS:
//   - Member 1 Samson Okuthe, OKTSAM001
//   - Member 2 Nyakallo Peete, PTXNYA001

// File        : GPR.v
// Description : General Purpose Register File.
//               8 registers, each 16 bits wide (R0–R7).
//               Two asynchronous (combinational) read ports.
//               One synchronous (clocked, positive-edge) write port.
//
// Task 2 — Student Implementation Required
// =============================================================================

`timescale 1ns / 1ps
`include "../src/Parameter.v"

module GPR (
    input        clk,

    // --- Write port (synchronous) -------------------------------------------
    input        reg_write_en,          // Write enable; write occurs on posedge clk
    input  [2:0] reg_write_dest,        // Destination register address (0–7)
    input  [15:0] reg_write_data,       // Data to write

    // --- Read port 1 (asynchronous) ------------------------------------------
    input  [2:0] reg_read_addr_1,       // Source register 1 address (RS1)
    output [15:0] reg_read_data_1,      // Data from RS1 — available immediately

    // --- Read port 2 (asynchronous) ------------------------------------------
    input  [2:0] reg_read_addr_2,       // Source register 2 address (RS2 / WS for I-type)
    output [15:0] reg_read_data_2       // Data from RS2 — available immediately
);

    // -------------------------------------------------------------------------
    // TODO: Declare the internal register array.
    //       You need an array of 8 registers, each 16 bits wide.
    //
    //       reg [15:0] reg_array [7:0];
    // -------------------------------------------------------------------------
    reg [15:0] reg_array [7:0];


    // -------------------------------------------------------------------------
    // TODO: Initialise all registers to zero at simulation start.
    //       Use an initial block with a for loop.
    //
    //       integer i;
    //       initial begin
    //           for (i = 0; i < 8; i = i + 1)
    //               reg_array[i] <= 16'd0;
    //       end
    // -------------------------------------------------------------------------
    integer i;
    initial begin
        for (i = 0; i < 8; i = i + 1)
            reg_array[i] <= 16'd0;
    end


    // -------------------------------------------------------------------------
    // TODO: Implement the synchronous write port.
    //       Write reg_write_data to reg_array[reg_write_dest] on the rising
    //       clock edge, but only when reg_write_en is asserted.
    //
    //       Use: always @(posedge clk) begin
    //                if (reg_write_en)
    //                    reg_array[...] <= ...;
    //            end
    //
    //       IMPORTANT: Use non-blocking assignment (<=) here.
    //                  This models a real flip-flop-based register.
    // -------------------------------------------------------------------------
    always @(posedge clk) begin
        if (reg_write_en)
            reg_array[reg_write_dest] <= reg_write_data;
    end


    // -------------------------------------------------------------------------
    // TODO: Implement the two asynchronous read ports.
    //       Both outputs must be continuous (combinational) assignments.
    //       They must update immediately whenever the address inputs change.
    //
    //       assign reg_read_data_1 = reg_array[reg_read_addr_1];
    //       assign reg_read_data_2 = reg_array[reg_read_addr_2];
    //
    //       NOTE: Because reads are asynchronous and the write is synchronous,
    //       if reg_read_addr_1 == reg_write_dest when reg_write_en is high,
    //       the read port returns the OLD value (before the write commits).
    //       Document this write-before-read behaviour in your report.
    // -------------------------------------------------------------------------
    assign reg_read_data_1 = reg_array[reg_read_addr_1];
    assign reg_read_data_2 = reg_array[reg_read_addr_2];


endmodule

Practical-4/tb/GPR_tb.v
// =============================================================================
// EEE4120F Practical 4 — StarCore-1 Processor
// File        : GPR_tb.v
// =============================================================================
`timescale 1ns / 1ps
`include "../src/Parameter.v"

module GPR_tb;

    reg        clk;
    reg        reg_write_en;
    reg  [2:0] reg_write_dest;
    reg  [15:0] reg_write_data;
    reg  [2:0] reg_read_addr_1;
    reg  [2:0] reg_read_addr_2;
    wire [15:0] reg_read_data_1;
    wire [15:0] reg_read_data_2;

    GPR uut (
        .clk              (clk),
        .reg_write_en     (reg_write_en),
        .reg_write_dest   (reg_write_dest),
        .reg_write_data   (reg_write_data),
        .reg_read_addr_1  (reg_read_addr_1),
        .reg_read_data_1  (reg_read_data_1),
        .reg_read_addr_2  (reg_read_addr_2),
        .reg_read_data_2  (reg_read_data_2)
    );

    initial clk = 1'b0;
    always  #5 clk = ~clk;

    initial begin
        $dumpfile("../waves/gpr_tb.vcd");
        $dumpvars(0, GPR_tb);
    end

    integer fail_count;
    integer test_id;
    initial begin fail_count = 0; test_id = 1; end

    task check16;
        input [15:0] got;
        input [15:0] expected;
        input [63:0] id;
        begin
            if (got !== expected) begin
                $display("FAIL [T%0d]: got = 0x%h, expected = 0x%h", id, got, expected);
                fail_count = fail_count + 1;
            end else
                $display("PASS [T%0d]: value = 0x%h", id, got);
        end
    endtask

    // Unique value per register for independence testing
    reg [15:0] vals [0:7];
    integer i;

    initial begin
        $display("=== GPR Testbench ===");
        reg_write_en    = 1'b0;
        reg_write_dest  = 3'd0;
        reg_write_data  = 16'd0;
        reg_read_addr_1 = 3'd0;
        reg_read_addr_2 = 3'd0;

        vals[0] = 16'hA000; vals[1] = 16'hB001; vals[2] = 16'hC002; vals[3] = 16'hD003;
        vals[4] = 16'hE004; vals[5] = 16'hF005; vals[6] = 16'h1006; vals[7] = 16'h2007;

        @(posedge clk); #1; // let init settle

        // ── Group 1: Write and read back all 8 registers ─────────
        $display("--- Test Group 1: Write and read back all 8 registers ---");
        for (i = 0; i < 8; i = i + 1) begin
            reg_write_en   = 1'b1;
            reg_write_dest = i[2:0];
            reg_write_data = vals[i];
            @(posedge clk); #1;
            reg_write_en = 1'b0;
            reg_read_addr_1 = i[2:0]; #2;
            check16(reg_read_data_1, vals[i], test_id);
            test_id = test_id + 1;
        end

        // ── Group 2: Disabled write must not modify register ──────
        $display("--- Test Group 2: Disabled write must not modify register ---");
        reg_write_en   = 1'b0;
        reg_write_dest = 3'd0;
        reg_write_data = 16'hDEAD; // must NOT be written
        @(posedge clk); #1;
        reg_read_addr_1 = 3'd0; #2;
        check16(reg_read_data_1, vals[0], test_id); // original value still there
        test_id = test_id + 1;

        // ── Group 3: Simultaneous dual-port read ──────────────────
        $display("--- Test Group 3: Simultaneous dual-port read ---");
        reg_read_addr_1 = 3'd1;
        reg_read_addr_2 = 3'd3;
        #2;
        check16(reg_read_data_1, vals[1], test_id); test_id = test_id + 1;
        check16(reg_read_data_2, vals[3], test_id); test_id = test_id + 1;

        // ── Group 4: Read during write (observe write-before-read) ─
        $display("--- Test Group 4: Read address matches write address during write ---");
        reg_write_en    = 1'b1;
        reg_write_dest  = 3'd2;
        reg_write_data  = 16'hCAFE;
        reg_read_addr_1 = 3'd2;
        #2; // before clock edge — should see OLD value (async read)
        $display("INFO [T%0d]: Read during write = 0x%h (old value before posedge)",
                 test_id, reg_read_data_1);
        test_id = test_id + 1;
        @(posedge clk); #1;
        reg_write_en = 1'b0;
        #2;
        check16(reg_read_data_1, 16'hCAFE, test_id); // new value after write
        test_id = test_id + 1;

        // ── Summary ───────────────────────────────────────────────
        $display("");
        if (fail_count == 0)
            $display("=== ALL %0d TESTS PASSED ===", test_id - 1);
        else
            $display("=== %0d / %0d TESTS FAILED ===", fail_count, test_id - 1);

        $finish;
    end

endmodule

Practical-4/waves/gpr_tb.vcd
$date
	Wed Apr 22 04:23:59 2026
$end
$version
	Icarus Verilog
$end
$timescale
	1ps
$end
$scope module GPR_tb $end
$var wire 16 ! reg_read_data_2 [15:0] $end
$var wire 16 " reg_read_data_1 [15:0] $end
$var reg 1 # clk $end
$var reg 3 $ reg_read_addr_1 [2:0] $end
$var reg 3 % reg_read_addr_2 [2:0] $end
$var reg 16 & reg_write_data [15:0] $end
$var reg 3 ' reg_write_dest [2:0] $end
$var reg 1 ( reg_write_en $end
$var integer 32 ) fail_count [31:0] $end
$var integer 32 * i [31:0] $end
$var integer 32 + test_id [31:0] $end
$scope module uut $end
$var wire 1 # clk $end
$var wire 3 , reg_read_addr_1 [2:0] $end
$var wire 3 - reg_read_addr_2 [2:0] $end
$var wire 16 . reg_read_data_1 [15:0] $end
$var wire 16 / reg_read_data_2 [15:0] $end
$var wire 16 0 reg_write_data [15:0] $end
$var wire 3 1 reg_write_dest [2:0] $end
$var wire 1 ( reg_write_en $end
$var integer 32 2 i [31:0] $end
$upscope $end
$scope task check16 $end
$var reg 16 3 expected [15:0] $end
$var reg 16 4 got [15:0] $end
$var reg 64 5 id [63:0] $end
$upscope $end
$upscope $end
$enddefinitions $end
$comment Show the parameter values. $end
$dumpall
$end
#0
$dumpvars
bx 5
bx 4
bx 3
b1000 2
b0 1
b0 0
b0 /
b0 .
b0 -
b0 ,
b1 +
bx *
b0 )
0(
b0 '
b0 &
b0 %
b0 $
0#
b0 "
b0 !
$end
#5000
1#
#6000
b1010000000000000 &
b1010000000000000 0
1(
b0 *
#10000
0#
#15000
b1010000000000000 "
b1010000000000000 .
b1010000000000000 !
b1010000000000000 /
1#
#16000
0(
#18000
b1011000000000001 &
b1011000000000001 0
b1 '
b1 1
1(
b1 *
b10 +
b1 5
b1010000000000000 3
b1010000000000000 4
#20000
0#
#25000
1#
#26000
b1011000000000001 "
b1011000000000001 .
b1 $
b1 ,
0(
#28000
b1100000000000010 &
b1100000000000010 0
b10 '
b10 1
1(
b10 *
b11 +
b10 5
b1011000000000001 3
b1011000000000001 4
#30000
0#
#35000
1#
#36000
b1100000000000010 "
b1100000000000010 .
b10 $
b10 ,
0(
#38000
b1101000000000011 &
b1101000000000011 0
b11 '
b11 1
1(
b11 *
b100 +
b11 5
b1100000000000010 3
b1100000000000010 4
#40000
0#
#45000
1#
#46000
b1101000000000011 "
b1101000000000011 .
b11 $
b11 ,
0(
#48000
b1110000000000100 &
b1110000000000100 0
b100 '
b100 1
1(
b100 *
b101 +
b100 5
b1101000000000011 3
b1101000000000011 4
#50000
0#
#55000
1#
#56000
b1110000000000100 "
b1110000000000100 .
b100 $
b100 ,
0(
#58000
b1111000000000101 &
b1111000000000101 0
b101 '
b101 1
1(
b101 *
b110 +
b101 5
b1110000000000100 3
b1110000000000100 4
#60000
0#
#65000
1#
#66000
b1111000000000101 "
b1111000000000101 .
b101 $
b101 ,
0(
#68000
b1000000000110 &
b1000000000110 0
b110 '
b110 1
1(
b110 *
b111 +
b110 5
b1111000000000101 3
b1111000000000101 4
#70000
0#
#75000
1#
#76000
b1000000000110 "
b1000000000110 .
b110 $
b110 ,
0(
#78000
b10000000000111 &
b10000000000111 0
b111 '
b111 1
1(
b111 *
b1000 +
b111 5
b1000000000110 3
b1000000000110 4
#80000
0#
#85000
1#
#86000
b10000000000111 "
b10000000000111 .
b111 $
b111 ,
0(
#88000
b1101111010101101 &
b1101111010101101 0
b0 '
b0 1
b1000 *
b1001 +
b1000 5
b10000000000111 3
b10000000000111 4
#90000
0#
#95000
1#
#96000
b1010000000000000 "
b1010000000000000 .
b0 $
b0 ,
#98000
b1101000000000011 !
b1101000000000011 /
b11 %
b11 -
b1011000000000001 "
b1011000000000001 .
b1 $
b1 ,
b1010 +
b1001 5
b1010000000000000 3
b1010000000000000 4
#100000
b1100000000000010 "
b1100000000000010 .
b10 $
b10 ,
b1100101011111110 &
b1100101011111110 0
b10 '
b10 1
1(
b1100 +
b1011 5
b1101000000000011 3
b1101000000000011 4
0#
#102000
b1101 +
#105000
b1100101011111110 "
b1100101011111110 .
1#
#106000
0(
#108000
b1110 +
b1101 5
b1100101011111110 3
b1100101011111110 4
