Practical-4/Practical-4/src/Parameter.v
// =========================================================================
// Practical 4: StarCore-1 — Single-Cycle Processor in Verilog
// =========================================================================
//
// GROUP NUMBER: 22
//
// MEMBERS:
//   - Member 1 Samson Okuthe, OKTSAM001
//   - Member 2 Nyakallo Peete, PTXNYA001

// File        : Parameter.v
// Description : Shared compile-time parameters used across all modules.
//               Include this file at the top of every .v file:
//                   `include "../src/Parameter.v"
// =============================================================================

`ifndef PARAMETER_H_
`define PARAMETER_H_

// ---------------------------------------------------------------------------
// Memory dimensions
// ---------------------------------------------------------------------------
`define COL     16          // Data/instruction word width (bits)
`define ROW_I   16          // Instruction memory depth (words, 16 x 16-bit)
`define ROW_D    8          // Data memory depth (words,  8 x 16-bit)

// ---------------------------------------------------------------------------
// Simulation control
// Increase SIM_TIME if your test program needs more clock cycles to complete.
// At 10 ns per clock (100 MHz) each #10 is one half-period; 320 ns = 16 cycles.
// ---------------------------------------------------------------------------
`define SIM_TIME  #640      // Total simulation time for integration testbench

// ---------------------------------------------------------------------------
// Output file for data-memory dump (used in DataMemory.v $fmonitor)
// ---------------------------------------------------------------------------
`define DMEM_LOG  "./waves/dmem_log.txt"

`endif  // PARAMETER_H_

Practical-4/src/InstructionMemory.v
// =========================================================================
// Practical 4: StarCore-1 — Single-Cycle Processor in Verilog
// =========================================================================
// File        : InstructionMemory.v
// Description : 16-word instruction ROM. Loaded from ./test/test.prog.

`timescale 1ns / 1ps
`include "../src/Parameter.v"

module InstructionMemory (
    input  [15:0] pc,
    output [15:0] instruction
);

    reg [`COL-1:0] memory [`ROW_I-1:0];

    // PC is byte-addressed; word index = pc[4:1]
    wire [3:0] rom_addr = pc[4:1];

    initial begin
        $readmemb("./test.prog", memory, 0, 14);
    end

    assign instruction = memory[rom_addr];

endmodule

Practical-4/tb/InstructionMemory_tb.v
// =============================================================================
// EEE4120F Practical 4 — StarCore-1 Processor
// File        : InstructionMemory_tb.v
// =============================================================================
`timescale 1ns / 1ps
`include "../src/Parameter.v"

module InstructionMemory_tb;

    reg  [15:0] pc;
    wire [15:0] instruction;

    InstructionMemory uut (.pc(pc), .instruction(instruction));

    initial begin
        $dumpfile("../waves/im_tb.vcd");
        $dumpvars(0, InstructionMemory_tb);
    end

    integer fail_count;
    integer test_id;
    integer i;

    // Expected instructions — match test.prog exactly (official skeleton values)
    reg [15:0] expected [0:14];

    initial begin
        fail_count = 0;
        test_id    = 1;

        $display("=== InstructionMemory Testbench ===");

        // Populate expected array from test.prog contents
        expected[0]  = 16'b0000010000000000; // LD  R0, 0(R0)
        expected[1]  = 16'b0000010001000001; // LD  R1, 1(R0)
        expected[2]  = 16'b0010000001010000; // ADD R2, R0, R1
        expected[3]  = 16'b0001001010000000; // ST  R2, 0(R1)
        expected[4]  = 16'b0011000001010000; // SUB R2, R0, R1
        expected[5]  = 16'b0111000001010000; // AND R2, R0, R1
        expected[6]  = 16'b1000000001010000; // OR  R2, R0, R1
        expected[7]  = 16'b1001000001010000; // SLT R2, R0, R1
        expected[8]  = 16'b0010000000000000; // ADD R0, R0, R0
        expected[9]  = 16'b1011000001000001; // BEQ R0, R1, +1
        expected[10] = 16'b1100000001000000; // BNE R0, R1, +0
        expected[11] = 16'b1101000000000000; // JMP 0
        expected[12] = 16'b0000000000000000; // (padding)
        expected[13] = 16'b0000000000000000; // (padding)
        expected[14] = 16'b0000000000000000; // (padding)

        // Walk PC through all 15 word-aligned addresses (0, 2, 4 ... 28)
        // Output is combinational — no clock needed, just settle time
        for (i = 0; i < 15; i = i + 1) begin
            pc = i * 2; #5;
            if (instruction !== expected[i]) begin
                $display("FAIL [T%0d]: PC=0x%h  got=%b  exp=%b",
                         test_id, pc, instruction, expected[i]);
                fail_count = fail_count + 1;
            end else
                $display("PASS [T%0d]: PC=0x%h  instr=%b", test_id, pc, instruction);
            test_id = test_id + 1;
        end

        $display("");
        if (fail_count == 0)
            $display("=== ALL %0d TESTS PASSED ===", test_id - 1);
        else
            $display("=== %0d / %0d TESTS FAILED ===", fail_count, test_id - 1);
        $finish;
    end

endmodule

Practical-4/waves/im_tb.vcd
$date
	Wed Apr 22 04:24:00 2026
$end
$version
	Icarus Verilog
$end
$timescale
	1ps
$end
$scope module InstructionMemory_tb $end
$var wire 16 ! instruction [15:0] $end
$var reg 16 " pc [15:0] $end
$var integer 32 # fail_count [31:0] $end
$var integer 32 $ i [31:0] $end
$var integer 32 % test_id [31:0] $end
$scope module uut $end
$var wire 16 & instruction [15:0] $end
$var wire 16 ' pc [15:0] $end
$var wire 4 ( rom_addr [3:0] $end
$upscope $end
$upscope $end
$enddefinitions $end
$comment Show the parameter values. $end
$dumpall
$end
#0
$dumpvars
b0 (
b0 '
b10000000000 &
b1 %
b0 $
b0 #
b0 "
b10000000000 !
$end
#5000
b10001000001 !
b10001000001 &
b1 (
b10 "
b10 '
b1 $
b10 %
#10000
b10000001010000 !
b10000001010000 &
b10 (
b100 "
b100 '
b10 $
b11 %
#15000
b1001010000000 !
b1001010000000 &
b11 (
b110 "
b110 '
b11 $
b100 %
#20000
b11000001010000 !
b11000001010000 &
b100 (
b1000 "
b1000 '
b100 $
b101 %
#25000
b111000001010000 !
b111000001010000 &
b101 (
b1010 "
b1010 '
b101 $
b110 %
#30000
b1000000001010000 !
b1000000001010000 &
b110 (
b1100 "
b1100 '
b110 $
b111 %
#35000
b1001000001010000 !
b1001000001010000 &
b111 (
b1110 "
b1110 '
b111 $
b1000 %
#40000
b10000000000000 !
b10000000000000 &
b1000 (
b10000 "
b10000 '
b1000 $
b1001 %
#45000
b1011000001000001 !
b1011000001000001 &
b1001 (
b10010 "
b10010 '
b1001 $
b1010 %
#50000
b1100000001000000 !
b1100000001000000 &
b1010 (
b10100 "
b10100 '
b1010 $
b1011 %
#55000
b1101000000000000 !
b1101000000000000 &
b1011 (
b10110 "
b10110 '
b1011 $
b1100 %
#60000
b0 !
b0 &
b1100 (
b11000 "
b11000 '
b1100 $
b1101 %
#65000
b1101 (
b11010 "
b11010 '
b1101 $
b1110 %
#70000
b1110 (
b11100 "
b11100 '
b1110 $
b1111 %
#75000
b1111 $
b10000 %
